visualastro/DataCube.py
visualastro/ExtractedSpectrum.py
visualastro/FitsFile.py
visualastro/__init__.py
visualastro/data_cube.py
visualastro/data_cube_utils.py
visualastro/error_propagation.py
visualastro/fits_utils.py
visualastro/io.py
visualastro/numerical_utils.py
visualastro/plot_utils.py
visualastro/plotting.py
visualastro/spectra.py
visualastro/spectra_utils.py
visualastro/units.py
visualastro/va_config.py
visualastro/validation.py
visualastro/visual_plots.py
visualastro/wcs_utils.py
visualastro/stylelib/astro.mplstyle
visualastro/stylelib/default.mplstyle
visualastro/stylelib/latex.mplstyle
visualastro/stylelib/minimal.mplstyle
visualastro/stylelib/smplot.mplstyle
visualastro-0.1.2.dist-info/LICENSE
visualastro-0.1.2.dist-info/METADATA
visualastro-0.1.2.dist-info/WHEEL
visualastro-0.1.2.dist-info/top_level.txt
visualastro-0.1.2.dist-info/RECORD
