Metadata-Version: 2.2
Name: visualastro
Version: 0.1.2
Summary: Astro data analysis and plotting package
Author-email: Elko Gerville-Reache <elkogerville@gmail.com>
License: MIT
Project-URL: Homepage, https://github.com/elkogerville/VisualAstro
Classifier: Programming Language :: Python :: 3
Classifier: License :: OSI Approved :: MIT License
Classifier: Operating System :: OS Independent
Requires-Python: <3.13,>=3.10
License-File: LICENSE
Requires-Dist: astropy
Requires-Dist: dust_extinction
Requires-Dist: matplotlib
Requires-Dist: numpy
Requires-Dist: regions
Requires-Dist: reproject
Requires-Dist: scipy
Requires-Dist: spectral_cube
Requires-Dist: specutils
Requires-Dist: tqdm
